obs_scoreboard-1.1.dist-info/licenses/LICENSE
scores/__init__.py
scores/scores.py
scores/fonts/SpaceMono-Bold.ttf
scores/fonts/SpaceMono-BoldItalic.ttf
scores/fonts/SpaceMono-Italic.ttf
scores/fonts/SpaceMono-Regular.ttf
scores/images/GUI.png
scores/images/OBS-overlay-example.png
obs_scoreboard-1.1.dist-info/METADATA
obs_scoreboard-1.1.dist-info/WHEEL
obs_scoreboard-1.1.dist-info/entry_points.txt
obs_scoreboard-1.1.dist-info/top_level.txt
obs_scoreboard-1.1.dist-info/RECORD
