Metadata-Version: 2.4
Name: obs-scoreboard
Version: 1.1
Summary: Simple python-powered scoreboard for use with my online webcasts.
Home-page: https://github.com/gsl4295/scores
Author: 
License: MIT
License-File: LICENSE
Requires-Dist: dearpygui
Dynamic: description
Dynamic: description-content-type
Dynamic: home-page
Dynamic: license
Dynamic: license-file
Dynamic: requires-dist
Dynamic: summary
